{"version":3,"kind":"Notebook","sha256":"a26a6fe262749bd3158f1d12cab6212fad742fb8cfc18270888e2d0630b21dbb","slug":"pnnl-bdg3-2","location":"/examples/pnnl-bdg3-2.md","dependencies":[],"frontmatter":{"title":"PNNL Example Building 3 Model 2","kernelspec":{"name":"open223-models","display_name":"open223-models","language":"python"},"jupytext":{"formats":"md:myst","text_representation":{"extension":".md","format_name":"myst"}},"content_includes_title":true,"github":"https://github.com/open223/models.open223.info","numbering":{"title":{"offset":1}},"source_url":"https://github.com/open223/models.open223.info/blob/main/examples/pnnl-bdg3-2.md","edit_url":"https://github.com/open223/models.open223.info/edit/main/examples/pnnl-bdg3-2.md","thumbnail":"/build/3cbed6eefcb19ba2da4ac39abadac135.png","exports":[{"format":"md","filename":"pnnl-bdg3-2.md","url":"/build/pnnl-bdg3-2-8af7292fbebf8db8096df84dad960499.md"}]},"mdast":{"type":"root","children":[{"type":"block","children":[{"type":"admonition","kind":"warning","children":[{"type":"admonitionTitle","children":[{"type":"text","value":"Warning","key":"WVyuqhlzEk"}],"key":"EpCHCvveeD"},{"type":"paragraph","position":{"start":{"line":14,"column":1},"end":{"line":14,"column":1}},"children":[{"type":"text","value":"This model has not been updated since the last revision of the 223P ontology and it may not pass validation.","position":{"start":{"line":14,"column":1},"end":{"line":14,"column":1}},"key":"V1nD3SynqE"}],"key":"ovLIVZ2UXb"},{"type":"list","ordered":false,"spread":false,"position":{"start":{"line":16,"column":1},"end":{"line":17,"column":1}},"children":[{"type":"listItem","spread":true,"position":{"start":{"line":16,"column":1},"end":{"line":16,"column":1}},"children":[{"type":"paragraph","children":[{"type":"text","value":"223P was last updated on 2026-05-21 11:27:59","position":{"start":{"line":16,"column":1},"end":{"line":16,"column":1}},"key":"lqTMFpn7V1"}],"key":"HhXS8CEi3G"}],"key":"uoBYaznaQw"},{"type":"listItem","spread":true,"position":{"start":{"line":17,"column":1},"end":{"line":17,"column":1}},"children":[{"type":"paragraph","children":[{"type":"text","value":"model file was last updated on 2024-09-14 12:12:25","position":{"start":{"line":17,"column":1},"end":{"line":17,"column":1}},"key":"KbfAP7BiPc"}],"key":"RPofSJI102"}],"key":"dcPdAafUyP"}],"key":"Psrhq9JRK1"}],"key":"ViECq5qIjt"},{"type":"heading","depth":1,"position":{"start":{"line":20,"column":1},"end":{"line":20,"column":1}},"children":[{"type":"text","value":"PNNL Example Building 3 Model 2","position":{"start":{"line":20,"column":1},"end":{"line":20,"column":1}},"key":"RWCBXjeHHy"}],"identifier":"pnnl-example-building-3-model-2","label":"PNNL Example Building 3 Model 2","html_id":"pnnl-example-building-3-model-2","implicit":true,"key":"ymaOfunPKl"},{"type":"paragraph","position":{"start":{"line":22,"column":1},"end":{"line":25,"column":1}},"children":[{"type":"text","value":"Exammple Building 3 is a real-world medium-sized office building.\nIt is approximately 67,000 square feet in size, contains 2 floors, 27 space types, and 469 rooms. Labels have been anonymized, and are not interpretable.\nIt uses an underfloor air distribution system with fan-powered terminal reheat coils for perimeter zones. Four roof-top units with VAV are located on the roof.\nThe lighting system primariliy uses fluorescent luminaires and zone-based lighting controllers that communicate with user interface devices and wireless gatetways over DALI networks. The gateways collect occupancy and light sensor data over an ISM-band wireless network.","position":{"start":{"line":22,"column":1},"end":{"line":22,"column":1}},"key":"xye0rJIwAN"}],"key":"XKSrBx9lKN"},{"type":"paragraph","position":{"start":{"line":27,"column":1},"end":{"line":28,"column":1}},"children":[{"type":"text","value":"Example Building 3 Model 2 is provided by Pacific Northwest National Laboratory.\nSee ","position":{"start":{"line":27,"column":1},"end":{"line":27,"column":1}},"key":"LyaneP9qJ7"},{"type":"link","url":"lbnl-bdg3-2.md","position":{"start":{"line":27,"column":1},"end":{"line":27,"column":1}},"children":[{"type":"text","value":"LBNL Example Building 3 model 1","position":{"start":{"line":27,"column":1},"end":{"line":27,"column":1}},"key":"j5uMHk5U3x"}],"urlSource":"lbnl-bdg3-2.md","key":"l94TfAtlVl"},{"type":"text","value":" for a different modeling approach for the same building.","position":{"start":{"line":27,"column":1},"end":{"line":27,"column":1}},"key":"JEsOuoGpth"}],"key":"uqMmCcQNzF"},{"type":"heading","depth":2,"position":{"start":{"line":30,"column":1},"end":{"line":30,"column":1}},"children":[{"type":"text","value":"Contents","position":{"start":{"line":30,"column":1},"end":{"line":30,"column":1}},"key":"rbrBv0BJlO"}],"identifier":"contents","label":"Contents","html_id":"contents","implicit":true,"key":"FbtNr3glKr"},{"type":"paragraph","position":{"start":{"line":32,"column":1},"end":{"line":32,"column":1}},"children":[{"type":"text","value":"This model contains a complete representation of the building architecture and electrical/lighting system, and a partial representation of the lighting control system.","position":{"start":{"line":32,"column":1},"end":{"line":32,"column":1}},"key":"g4vRnf2S6E"}],"key":"NaHZmiPBVY"},{"type":"paragraph","position":{"start":{"line":34,"column":1},"end":{"line":34,"column":1}},"children":[{"type":"text","value":"In addition to the s223 ontology, the model uses the ","position":{"start":{"line":34,"column":1},"end":{"line":34,"column":1}},"key":"XgYRXJ1Zce"},{"type":"link","url":"https://dev.realestatecore.io/ontology/","position":{"start":{"line":34,"column":1},"end":{"line":34,"column":1}},"children":[{"type":"text","value":"Real Estate Core ontology","position":{"start":{"line":34,"column":1},"end":{"line":34,"column":1}},"key":"PtMTCIoXsV"}],"urlSource":"https://dev.realestatecore.io/ontology/","key":"sL84WBGyw5"},{"type":"text","value":" to describe space types. The Real Estate Core ontology is extended by defining 2 subclasses for rec:Office.","position":{"start":{"line":34,"column":1},"end":{"line":34,"column":1}},"key":"RKyZMdUE4C"}],"key":"XXcfub9dHw"},{"type":"code","lang":"ttl","value":"recx:OpenOffice rdfs:subClassOf rec:Office;\n  rdfs:label \"Open Office\".\nrecx:PrivateOffice rdfs:subClassOf rec:Office;\n  rdfs:label \"Private Office\".","position":{"start":{"line":35,"column":1},"end":{"line":40,"column":1}},"key":"wwRpq9RAwQ"},{"type":"heading","depth":2,"position":{"start":{"line":42,"column":1},"end":{"line":42,"column":1}},"children":[{"type":"text","value":"Source","position":{"start":{"line":42,"column":1},"end":{"line":42,"column":1}},"key":"VKALQpPWVn"}],"identifier":"source","label":"Source","html_id":"source","implicit":true,"key":"Sn0pzfT7vm"},{"type":"paragraph","position":{"start":{"line":44,"column":1},"end":{"line":44,"column":1}},"children":[{"type":"text","value":"The model was created from souce data consisting of a Revit building information model (BIM) exported via a ","position":{"start":{"line":44,"column":1},"end":{"line":44,"column":1}},"key":"dEAHJ9m60G"},{"type":"link","url":"https://speckle.systems/","position":{"start":{"line":44,"column":1},"end":{"line":44,"column":1}},"children":[{"type":"text","value":"Speckle","position":{"start":{"line":44,"column":1},"end":{"line":44,"column":1}},"key":"TYik51ALDK"}],"urlSource":"https://speckle.systems/","key":"nFGDh9qtnd"},{"type":"text","value":" interface.","position":{"start":{"line":44,"column":1},"end":{"line":44,"column":1}},"key":"rIKfyvj199"}],"key":"Rio7GQVSEK"},{"type":"heading","depth":3,"position":{"start":{"line":46,"column":1},"end":{"line":46,"column":1}},"children":[{"type":"text","value":"Speckle view of rooms and lighting fixtures","position":{"start":{"line":46,"column":1},"end":{"line":46,"column":1}},"key":"mZh74dzsSy"}],"identifier":"speckle-view-of-rooms-and-lighting-fixtures","label":"Speckle view of rooms and lighting fixtures","html_id":"speckle-view-of-rooms-and-lighting-fixtures","implicit":true,"key":"pdpbB8eTPR"},{"type":"image","url":"/build/3cbed6eefcb19ba2da4ac39abadac135.png","alt":"image","width":1378,"key":"LtZQ64YoJ3","urlSource":"https://github.com/user-attachments/assets/57981a65-937a-4c4b-9151-978073976d14"},{"type":"paragraph","position":{"start":{"line":49,"column":1},"end":{"line":49,"column":1}},"children":[{"type":"text","value":"Model instance data have a prefix that is resolvable to a Speckle URL.","position":{"start":{"line":49,"column":1},"end":{"line":49,"column":1}},"key":"Fdwm3ggkCa"}],"key":"mkWJMUHv5E"},{"type":"code","lang":"ttl","value":"@prefix bdg3: <http://speckle.xyz/streams/bf7685a6aa/objects/>","position":{"start":{"line":50,"column":1},"end":{"line":52,"column":1}},"key":"HfKOaYAdFr"},{"type":"paragraph","position":{"start":{"line":54,"column":1},"end":{"line":54,"column":1}},"children":[{"type":"text","value":"For example, the following luminaire resolves to ","position":{"start":{"line":54,"column":1},"end":{"line":54,"column":1}},"key":"ZjQp6CmAZI"},{"type":"link","url":"http://speckle.xyz/streams/bf7685a6aa/objects/978e64f766e711a6cc73f3a4d4c0a3e9","position":{"start":{"line":54,"column":1},"end":{"line":54,"column":1}},"children":[{"type":"text","value":"http://​speckle​.xyz​/streams​/bf7685a6aa​/objects​/978e64f766e711a6cc73f3a4d4c0a3e9","position":{"start":{"line":54,"column":1},"end":{"line":54,"column":1}},"key":"JF5iUiiPVO"}],"urlSource":"http://speckle.xyz/streams/bf7685a6aa/objects/978e64f766e711a6cc73f3a4d4c0a3e9","key":"JTpL4GbpuD"},{"type":"text","value":" :","position":{"start":{"line":54,"column":1},"end":{"line":54,"column":1}},"key":"vwEI61oxUZ"}],"key":"Ts5upGoZz7"},{"type":"code","lang":"ttl","value":"bdg3:978e64f766e711a6cc73f3a4d4c0a3e9 a s223:Luminaire","position":{"start":{"line":55,"column":1},"end":{"line":57,"column":1}},"key":"JJHpWimWy2"},{"type":"heading","depth":2,"position":{"start":{"line":59,"column":1},"end":{"line":59,"column":1}},"children":[{"type":"text","value":"Downloads","position":{"start":{"line":59,"column":1},"end":{"line":59,"column":1}},"key":"ped5LQAFtP"}],"identifier":"downloads","label":"Downloads","html_id":"downloads","implicit":true,"key":"W6iWW2nUrE"},{"type":"list","ordered":false,"spread":false,"position":{"start":{"line":61,"column":1},"end":{"line":65,"column":1}},"children":[{"type":"listItem","spread":true,"position":{"start":{"line":61,"column":1},"end":{"line":61,"column":1}},"children":[{"type":"paragraph","children":[{"type":"link","url":"/compiled/pnnl-bdg3-2.ttl","children":[{"type":"text","value":"Turtle file (compiled)","key":"cafBKXHzIe"}],"urlSource":"/compiled/pnnl-bdg3-2.ttl","key":"euLCgbpdoe"}],"key":"f1fMspw7Wk"}],"key":"Zpq36sndAZ"},{"type":"listItem","spread":true,"position":{"start":{"line":62,"column":1},"end":{"line":62,"column":1}},"children":[{"type":"paragraph","children":[{"type":"link","url":"/withimports/pnnl-bdg3-2.ttl","children":[{"type":"text","value":"Turtle file (with all imports)","key":"LxHx5tAYQm"}],"urlSource":"/withimports/pnnl-bdg3-2.ttl","key":"WiWqmbPKP5"}],"key":"p1czwlc7fL"}],"key":"eH4qH6IuWC"},{"type":"listItem","spread":true,"position":{"start":{"line":63,"column":1},"end":{"line":63,"column":1}},"children":[{"type":"paragraph","children":[{"type":"link","url":"/pnnl-bdg3-2.ttl","children":[{"type":"text","value":"Turtle file (original)","key":"Q2ZkSItOwM"}],"urlSource":"/pnnl-bdg3-2.ttl","key":"BRRHHSnQed"}],"key":"NQCwBQ27MQ"}],"key":"SrV4PTIE2x"},{"type":"listItem","spread":true,"position":{"start":{"line":64,"column":1},"end":{"line":65,"column":1}},"children":[{"type":"paragraph","children":[{"type":"link","url":"/pnnl-bdg3-2.jsonld","children":[{"type":"text","value":"JSON-LD file (original)","key":"NQjjMeFxs1"}],"urlSource":"/pnnl-bdg3-2.jsonld","key":"Cbt0NotmZ7"}],"key":"nyhlhJnwOC"}],"key":"JfpDS8UUqd"}],"key":"casUbjIQ5i"},{"type":"details","children":[{"type":"summary","children":[{"type":"text","value":"What are these files?","key":"EmnNLoBABc"}],"key":"VaEgQXcCMH"},{"type":"list","ordered":false,"start":null,"spread":false,"children":[{"type":"listItem","spread":false,"checked":null,"children":[{"type":"paragraph","children":[{"type":"strong","children":[{"type":"text","value":"Turtle file (original)","key":"usSAXXElDB"}],"key":"XropRlenSL"},{"type":"text","value":": This is the original source Turtle file that was provided to ","key":"AGFwd3OQ64"},{"type":"inlineCode","value":"models.open223.info","key":"ThhVyQG2LH"},{"type":"text","value":", usually as the output of some model creation tool.","key":"sv81uDmPNF"}],"key":"N0XlLVw9gz"}],"key":"ug1hXysfhJ"},{"type":"listItem","spread":false,"checked":null,"children":[{"type":"paragraph","children":[{"type":"strong","children":[{"type":"text","value":"Turtle file (compiled)","key":"FKG7xkZV1u"}],"key":"ZPEemlthyV"},{"type":"text","value":": This is the original Turtle file with all inferred relationships and values added through SHACL inference against the 223P ontology and other dependencies. ","key":"QNCTvCJe94"},{"type":"strong","children":[{"type":"text","value":"You should use this file for any further processing.","key":"CErtMhm5wf"}],"key":"AEgWxsA82f"},{"type":"text","value":" It does not contain any of the ontologies.","key":"AeaPXlKFSx"}],"key":"IB5QkqCDRa"}],"key":"a6ZPQlVUvX"},{"type":"listItem","spread":false,"checked":null,"children":[{"type":"paragraph","children":[{"type":"strong","children":[{"type":"text","value":"Turtle file (with all imports)","key":"ySRnLED93x"}],"key":"jQvCW9kGn9"},{"type":"text","value":": This is the compiled Turtle file with all imports included in the file (223P ontology, QUDT ontology, and others). This is helpful when you do not want to deal with downloading and managing ontology dependencies. It is also much larger than the compiled file.","key":"yRoszFwlhk"}],"key":"mj4JEnO77N"}],"key":"UybDRRyc9z"},{"type":"listItem","spread":false,"checked":null,"children":[{"type":"paragraph","children":[{"type":"strong","children":[{"type":"text","value":"JSON-LD file (original)","key":"O0JqaqRfON"}],"key":"PPvNBrj3bV"},{"type":"text","value":": This is the original Turtle file converted to the JSON-LD format.","key":"lfJDSXaebn"}],"key":"Af1eR17kzm"}],"key":"VPB7tzIUGY"}],"key":"bI5OfUIXe1"},{"type":"paragraph","children":[{"type":"link","url":"https://www.w3.org/TR/turtle/","children":[{"type":"text","value":"Turtle","key":"X655UFjxTj"}],"urlSource":"https://www.w3.org/TR/turtle/","key":"B60dhyJZAA"},{"type":"text","value":" is a syntax for RDF (Resource Description Framework) that is easy to read and write. It is a popular format for representing linked data. Parsers and serializers are available in many programming languages. ","key":"jmIMbJ9kc2"},{"type":"link","url":"https://json-ld.org","children":[{"type":"text","value":"JSON-LD","key":"Cs6TnlesBH"}],"urlSource":"https://json-ld.org","key":"YiV3Pti1mD"},{"type":"text","value":" is a JSON-based format for linked data that is easy to use with JavaScript and other web technologies.","key":"G9EPVtHtYf"}],"key":"TkuhZJDe0C"}],"key":"N447XrOdeF"},{"type":"heading","depth":2,"position":{"start":{"line":78,"column":1},"end":{"line":78,"column":1}},"children":[{"type":"text","value":"Queries","position":{"start":{"line":78,"column":1},"end":{"line":78,"column":1}},"key":"ddG9tAt5gd"}],"identifier":"queries","label":"Queries","html_id":"queries","implicit":true,"key":"TJ8xYoFsBQ"},{"type":"table","position":{"start":{"line":79,"column":1},"end":{"line":81,"column":1}},"children":[{"type":"tableRow","position":{"start":{"line":79,"column":1},"end":{"line":79,"column":1}},"children":[{"type":"tableCell","header":true,"position":{"start":{"line":79,"column":1},"end":{"line":79,"column":1}},"children":[{"type":"text","value":"Description","position":{"start":{"line":79,"column":1},"end":{"line":79,"column":1}},"key":"lbrx0rMsjr"}],"key":"a4QHpNL3SG"},{"type":"tableCell","header":true,"position":{"start":{"line":79,"column":1},"end":{"line":79,"column":1}},"children":[{"type":"text","value":"Query URL","position":{"start":{"line":79,"column":1},"end":{"line":79,"column":1}},"key":"VHRn4P9xnL"}],"key":"vu6uooui0k"}],"key":"JWQZIEN6Ka"},{"type":"tableRow","position":{"start":{"line":81,"column":1},"end":{"line":81,"column":1}},"children":[{"type":"tableCell","position":{"start":{"line":81,"column":1},"end":{"line":81,"column":1}},"children":[{"type":"text","value":"Select all triples from model.","position":{"start":{"line":81,"column":1},"end":{"line":81,"column":1}},"key":"fmHqH9roa8"}],"key":"AOz5IZ9kd0"},{"type":"tableCell","position":{"start":{"line":81,"column":1},"end":{"line":81,"column":1}},"children":[{"type":"link","url":"https://query.open223.info/?query=PREFIX+s223%3A+%3Chttp%3A%2F%2Fdata.ashrae.org%2Fstandard223%23%3E+PREFIX+unit%3A+%3Chttp%3A%2F%2Fqudt.org%2Fvocab%2Funit%2F%3E+PREFIX+rdfs%3A+%3Chttp%3A%2F%2Fwww.w3.org%2F2000%2F01%2Frdf-schema%23%3E+PREFIX+rdf%3A+%3Chttp%3A%2F%2Fwww.w3.org%2F1999%2F02%2F22-rdf-syntax-ns%23%3E+PREFIX+quantitykind%3A+%3Chttp%3A%2F%2Fqudt.org%2Fvocab%2Fquantitykind%2F%3E+PREFIX+qudt%3A+%3Chttp%3A%2F%2Fqudt.org%2Fschema%2Fqudt%2F%3E+PREFIX+sh%3A+%3Chttp%3A%2F%2Fwww.w3.org%2Fns%2Fshacl%23%3E+PREFIX+owl%3A+%3Chttp%3A%2F%2Fwww.w3.org%2F2002%2F07%2Fowl%23%3E+%0ASELECT+%2A+WHERE+%7B%0A%09+%3Fs+%3Fp+%3Fo+%0A%7D%0A+LIMIT+10&url=https%3A%2F%2Fmodels.open223.info%2Fwithimports%2Fpnnl-bdg3-2.ttl","children":[{"type":"text","value":"Query Link","key":"UFPcb453ys"}],"urlSource":"https://query.open223.info/?query=PREFIX+s223%3A+%3Chttp%3A%2F%2Fdata.ashrae.org%2Fstandard223%23%3E+PREFIX+unit%3A+%3Chttp%3A%2F%2Fqudt.org%2Fvocab%2Funit%2F%3E+PREFIX+rdfs%3A+%3Chttp%3A%2F%2Fwww.w3.org%2F2000%2F01%2Frdf-schema%23%3E+PREFIX+rdf%3A+%3Chttp%3A%2F%2Fwww.w3.org%2F1999%2F02%2F22-rdf-syntax-ns%23%3E+PREFIX+quantitykind%3A+%3Chttp%3A%2F%2Fqudt.org%2Fvocab%2Fquantitykind%2F%3E+PREFIX+qudt%3A+%3Chttp%3A%2F%2Fqudt.org%2Fschema%2Fqudt%2F%3E+PREFIX+sh%3A+%3Chttp%3A%2F%2Fwww.w3.org%2Fns%2Fshacl%23%3E+PREFIX+owl%3A+%3Chttp%3A%2F%2Fwww.w3.org%2F2002%2F07%2Fowl%23%3E+%0ASELECT+%2A+WHERE+%7B%0A%09+%3Fs+%3Fp+%3Fo+%0A%7D%0A+LIMIT+10&url=https%3A%2F%2Fmodels.open223.info%2Fwithimports%2Fpnnl-bdg3-2.ttl","key":"bL1oeNQxux"}],"key":"Iszxbxtzlp"}],"key":"oGW1WD29om"}],"key":"evaT9DWGWc"},{"type":"heading","depth":2,"position":{"start":{"line":83,"column":1},"end":{"line":83,"column":1}},"children":[{"type":"text","value":"Model Components","position":{"start":{"line":83,"column":1},"end":{"line":83,"column":1}},"key":"tKaSTJC4JO"}],"identifier":"model-components","label":"Model Components","html_id":"model-components","implicit":true,"key":"hUifSBzILg"},{"type":"table","position":{"start":{"line":84,"column":1},"end":{"line":95,"column":1}},"children":[{"type":"tableRow","position":{"start":{"line":84,"column":1},"end":{"line":84,"column":1}},"children":[{"type":"tableCell","header":true,"position":{"start":{"line":84,"column":1},"end":{"line":84,"column":1}},"children":[{"type":"text","value":"Parent Class","position":{"start":{"line":84,"column":1},"end":{"line":84,"column":1}},"key":"mmbIMFAciS"}],"key":"lSRNAAMBPl"},{"type":"tableCell","header":true,"position":{"start":{"line":84,"column":1},"end":{"line":84,"column":1}},"children":[{"type":"text","value":"Class","position":{"start":{"line":84,"column":1},"end":{"line":84,"column":1}},"key":"MJDrMNLIpn"}],"key":"gDaGPcmnhl"},{"type":"tableCell","header":true,"position":{"start":{"line":84,"column":1},"end":{"line":84,"column":1}},"children":[{"type":"text","value":"Instances","position":{"start":{"line":84,"column":1},"end":{"line":84,"column":1}},"key":"iPjQSf8sGh"}],"key":"IrheV79y4d"}],"key":"d6GVZvGIqm"},{"type":"tableRow","position":{"start":{"line":86,"column":1},"end":{"line":86,"column":1}},"children":[{"type":"tableCell","position":{"start":{"line":86,"column":1},"end":{"line":86,"column":1}},"children":[{"type":"link","url":"https://explore.open223.info/s223/Equipment.html","position":{"start":{"line":86,"column":1},"end":{"line":86,"column":1}},"children":[{"type":"text","value":"Equipment","position":{"start":{"line":86,"column":1},"end":{"line":86,"column":1}},"key":"C34C6Pe40U"}],"urlSource":"https://explore.open223.info/s223/Equipment.html","key":"KxRYWXYuWq"}],"key":"rtFdmcYrVQ"},{"type":"tableCell","position":{"start":{"line":86,"column":1},"end":{"line":86,"column":1}},"children":[{"type":"link","url":"https://explore.open223.info/s223/Luminaire.html","position":{"start":{"line":86,"column":1},"end":{"line":86,"column":1}},"children":[{"type":"text","value":"Luminaire","position":{"start":{"line":86,"column":1},"end":{"line":86,"column":1}},"key":"Bccz7RzaNM"}],"urlSource":"https://explore.open223.info/s223/Luminaire.html","key":"QVCvJYpilq"}],"key":"focVNvdF2E"},{"type":"tableCell","position":{"start":{"line":86,"column":1},"end":{"line":86,"column":1}},"children":[{"type":"text","value":"713","position":{"start":{"line":86,"column":1},"end":{"line":86,"column":1}},"key":"bWyDFheAjP"}],"key":"c8yyvx6LeJ"}],"key":"YlmCfMp7OX"},{"type":"tableRow","position":{"start":{"line":87,"column":1},"end":{"line":87,"column":1}},"children":[{"type":"tableCell","position":{"start":{"line":87,"column":1},"end":{"line":87,"column":1}},"children":[{"type":"link","url":"https://explore.open223.info/s223/Equipment.html","position":{"start":{"line":87,"column":1},"end":{"line":87,"column":1}},"children":[{"type":"text","value":"Equipment","position":{"start":{"line":87,"column":1},"end":{"line":87,"column":1}},"key":"OuA4F3HUF5"}],"urlSource":"https://explore.open223.info/s223/Equipment.html","key":"gL3yxvR1AC"}],"key":"RVieCKGKU6"},{"type":"tableCell","position":{"start":{"line":87,"column":1},"end":{"line":87,"column":1}},"children":[{"type":"link","url":"https://explore.open223.info/s223/OccupantMotionSensor.html","position":{"start":{"line":87,"column":1},"end":{"line":87,"column":1}},"children":[{"type":"text","value":"OccupantMotionSensor","position":{"start":{"line":87,"column":1},"end":{"line":87,"column":1}},"key":"DYgmlavc4M"}],"urlSource":"https://explore.open223.info/s223/OccupantMotionSensor.html","key":"JK3GHcMdIK"}],"key":"rKpFTHps3d"},{"type":"tableCell","position":{"start":{"line":87,"column":1},"end":{"line":87,"column":1}},"children":[{"type":"text","value":"226","position":{"start":{"line":87,"column":1},"end":{"line":87,"column":1}},"key":"nfMk0zC1uS"}],"key":"yws1MSyetR"}],"key":"eRzni4c3vn"},{"type":"tableRow","position":{"start":{"line":88,"column":1},"end":{"line":88,"column":1}},"children":[{"type":"tableCell","position":{"start":{"line":88,"column":1},"end":{"line":88,"column":1}},"children":[{"type":"link","url":"https://explore.open223.info/s223/Equipment.html","position":{"start":{"line":88,"column":1},"end":{"line":88,"column":1}},"children":[{"type":"text","value":"Equipment","position":{"start":{"line":88,"column":1},"end":{"line":88,"column":1}},"key":"ftGE7sUdyj"}],"urlSource":"https://explore.open223.info/s223/Equipment.html","key":"kvmfee4ncf"}],"key":"cKwmT6rCqA"},{"type":"tableCell","position":{"start":{"line":88,"column":1},"end":{"line":88,"column":1}},"children":[{"type":"link","url":"https://explore.open223.info/s223/ElectricBreaker.html","position":{"start":{"line":88,"column":1},"end":{"line":88,"column":1}},"children":[{"type":"text","value":"ElectricBreaker","position":{"start":{"line":88,"column":1},"end":{"line":88,"column":1}},"key":"aPLlJFbXDs"}],"urlSource":"https://explore.open223.info/s223/ElectricBreaker.html","key":"dsJdKxv12e"}],"key":"za70d1vJva"},{"type":"tableCell","position":{"start":{"line":88,"column":1},"end":{"line":88,"column":1}},"children":[{"type":"text","value":"26","position":{"start":{"line":88,"column":1},"end":{"line":88,"column":1}},"key":"oLQW3e7RbS"}],"key":"AOxpG5hEzc"}],"key":"zhu1BMWBbb"},{"type":"tableRow","position":{"start":{"line":89,"column":1},"end":{"line":89,"column":1}},"children":[{"type":"tableCell","position":{"start":{"line":89,"column":1},"end":{"line":89,"column":1}},"children":[{"type":"link","url":"https://explore.open223.info/s223/Connection.html","position":{"start":{"line":89,"column":1},"end":{"line":89,"column":1}},"children":[{"type":"text","value":"Connection","position":{"start":{"line":89,"column":1},"end":{"line":89,"column":1}},"key":"CMCeTcVFcY"}],"urlSource":"https://explore.open223.info/s223/Connection.html","key":"p8kVAJIVgB"}],"key":"oCSFK6wzdw"},{"type":"tableCell","position":{"start":{"line":89,"column":1},"end":{"line":89,"column":1}},"children":[{"type":"link","url":"https://explore.open223.info/s223/ElectricWire.html","position":{"start":{"line":89,"column":1},"end":{"line":89,"column":1}},"children":[{"type":"text","value":"ElectricWire","position":{"start":{"line":89,"column":1},"end":{"line":89,"column":1}},"key":"lDMeFUy2gB"}],"urlSource":"https://explore.open223.info/s223/ElectricWire.html","key":"zplfdTHO4L"}],"key":"n3N7IyjRUp"},{"type":"tableCell","position":{"start":{"line":89,"column":1},"end":{"line":89,"column":1}},"children":[{"type":"text","value":"739","position":{"start":{"line":89,"column":1},"end":{"line":89,"column":1}},"key":"gV3DVv05Xu"}],"key":"B4jElh6m1g"}],"key":"lkhEbiBI1l"},{"type":"tableRow","position":{"start":{"line":90,"column":1},"end":{"line":90,"column":1}},"children":[{"type":"tableCell","position":{"start":{"line":90,"column":1},"end":{"line":90,"column":1}},"children":[{"type":"link","url":"https://explore.open223.info/s223/ConnectionPoint.html","position":{"start":{"line":90,"column":1},"end":{"line":90,"column":1}},"children":[{"type":"text","value":"ConnectionPoint","position":{"start":{"line":90,"column":1},"end":{"line":90,"column":1}},"key":"fYMykk4Y34"}],"urlSource":"https://explore.open223.info/s223/ConnectionPoint.html","key":"C6hzhWQXmR"}],"key":"pmWrpznhBU"},{"type":"tableCell","position":{"start":{"line":90,"column":1},"end":{"line":90,"column":1}},"children":[{"type":"link","url":"https://explore.open223.info/s223/OutletConnectionPoint.html","position":{"start":{"line":90,"column":1},"end":{"line":90,"column":1}},"children":[{"type":"text","value":"OutletConnectionPoint","position":{"start":{"line":90,"column":1},"end":{"line":90,"column":1}},"key":"vxghKCUXev"}],"urlSource":"https://explore.open223.info/s223/OutletConnectionPoint.html","key":"G2mcT7bwPa"}],"key":"iNbU5oSsNO"},{"type":"tableCell","position":{"start":{"line":90,"column":1},"end":{"line":90,"column":1}},"children":[{"type":"text","value":"1452","position":{"start":{"line":90,"column":1},"end":{"line":90,"column":1}},"key":"KAsHvEV80s"}],"key":"IAHI83qLbe"}],"key":"T9Et91AYUe"},{"type":"tableRow","position":{"start":{"line":91,"column":1},"end":{"line":91,"column":1}},"children":[{"type":"tableCell","position":{"start":{"line":91,"column":1},"end":{"line":91,"column":1}},"children":[{"type":"link","url":"https://explore.open223.info/s223/ConnectionPoint.html","position":{"start":{"line":91,"column":1},"end":{"line":91,"column":1}},"children":[{"type":"text","value":"ConnectionPoint","position":{"start":{"line":91,"column":1},"end":{"line":91,"column":1}},"key":"CwnMwqlZOG"}],"urlSource":"https://explore.open223.info/s223/ConnectionPoint.html","key":"VYOijhVqoK"}],"key":"XqwcEdE5dG"},{"type":"tableCell","position":{"start":{"line":91,"column":1},"end":{"line":91,"column":1}},"children":[{"type":"link","url":"https://explore.open223.info/s223/InletConnectionPoint.html","position":{"start":{"line":91,"column":1},"end":{"line":91,"column":1}},"children":[{"type":"text","value":"InletConnectionPoint","position":{"start":{"line":91,"column":1},"end":{"line":91,"column":1}},"key":"OGbA91BWrz"}],"urlSource":"https://explore.open223.info/s223/InletConnectionPoint.html","key":"EYXbgmvYPB"}],"key":"gdi3fF6gfa"},{"type":"tableCell","position":{"start":{"line":91,"column":1},"end":{"line":91,"column":1}},"children":[{"type":"text","value":"1452","position":{"start":{"line":91,"column":1},"end":{"line":91,"column":1}},"key":"vVcaLx2PDZ"}],"key":"oPCXbl6Wop"}],"key":"jkpO520J7l"},{"type":"tableRow","position":{"start":{"line":92,"column":1},"end":{"line":92,"column":1}},"children":[{"type":"tableCell","position":{"start":{"line":92,"column":1},"end":{"line":92,"column":1}},"children":[{"type":"link","url":"https://explore.open223.info/s223/DomainSpace.html","position":{"start":{"line":92,"column":1},"end":{"line":92,"column":1}},"children":[{"type":"text","value":"DomainSpace","position":{"start":{"line":92,"column":1},"end":{"line":92,"column":1}},"key":"GS9RhVjwfA"}],"urlSource":"https://explore.open223.info/s223/DomainSpace.html","key":"RZTKY3Ka7v"}],"key":"iN2BUUUmrS"},{"type":"tableCell","position":{"start":{"line":92,"column":1},"end":{"line":92,"column":1}},"children":[{"type":"link","url":"https://explore.open223.info/s223/.html","position":{"start":{"line":92,"column":1},"end":{"line":92,"column":1}},"children":[],"urlSource":"https://explore.open223.info/s223/.html","key":"fsqsOVEq6C"}],"key":"UwPfSBPyEx"},{"type":"tableCell","position":{"start":{"line":92,"column":1},"end":{"line":92,"column":1}},"children":[{"type":"text","value":"245","position":{"start":{"line":92,"column":1},"end":{"line":92,"column":1}},"key":"HB3b7L7ZGL"}],"key":"wv3GH4Z4kG"}],"key":"ikpQX27kfd"},{"type":"tableRow","position":{"start":{"line":93,"column":1},"end":{"line":93,"column":1}},"children":[{"type":"tableCell","position":{"start":{"line":93,"column":1},"end":{"line":93,"column":1}},"children":[{"type":"link","url":"https://explore.open223.info/s223/Zone.html","position":{"start":{"line":93,"column":1},"end":{"line":93,"column":1}},"children":[{"type":"text","value":"Zone","position":{"start":{"line":93,"column":1},"end":{"line":93,"column":1}},"key":"B4EKwQ2GLF"}],"urlSource":"https://explore.open223.info/s223/Zone.html","key":"npgF1MSavd"}],"key":"E9N0Jl84vs"},{"type":"tableCell","position":{"start":{"line":93,"column":1},"end":{"line":93,"column":1}},"children":[{"type":"link","url":"https://explore.open223.info/s223/.html","position":{"start":{"line":93,"column":1},"end":{"line":93,"column":1}},"children":[],"urlSource":"https://explore.open223.info/s223/.html","key":"vsXqmtITsj"}],"key":"hyeGDoB4pX"},{"type":"tableCell","position":{"start":{"line":93,"column":1},"end":{"line":93,"column":1}},"children":[{"type":"text","value":"236","position":{"start":{"line":93,"column":1},"end":{"line":93,"column":1}},"key":"jaZoo6aEQw"}],"key":"TQUGfJGW0Q"}],"key":"qLXINZHjN0"},{"type":"tableRow","position":{"start":{"line":94,"column":1},"end":{"line":94,"column":1}},"children":[{"type":"tableCell","position":{"start":{"line":94,"column":1},"end":{"line":94,"column":1}},"children":[{"type":"link","url":"https://explore.open223.info/s223/Property.html","position":{"start":{"line":94,"column":1},"end":{"line":94,"column":1}},"children":[{"type":"text","value":"Property","position":{"start":{"line":94,"column":1},"end":{"line":94,"column":1}},"key":"lJVy9ZbqEW"}],"urlSource":"https://explore.open223.info/s223/Property.html","key":"bFNH5zCFf9"}],"key":"WS4uOBZE8a"},{"type":"tableCell","position":{"start":{"line":94,"column":1},"end":{"line":94,"column":1}},"children":[{"type":"link","url":"https://explore.open223.info/s223/QuantifiableProperty.html","position":{"start":{"line":94,"column":1},"end":{"line":94,"column":1}},"children":[{"type":"text","value":"QuantifiableProperty","position":{"start":{"line":94,"column":1},"end":{"line":94,"column":1}},"key":"T0jWRNF8uk"}],"urlSource":"https://explore.open223.info/s223/QuantifiableProperty.html","key":"aBxIwR3IcF"}],"key":"iQi3ymsRfk"},{"type":"tableCell","position":{"start":{"line":94,"column":1},"end":{"line":94,"column":1}},"children":[{"type":"text","value":"443","position":{"start":{"line":94,"column":1},"end":{"line":94,"column":1}},"key":"fByOzyZX8P"}],"key":"keLaiF1ECK"}],"key":"SNHOyjPMpl"},{"type":"tableRow","position":{"start":{"line":95,"column":1},"end":{"line":95,"column":1}},"children":[{"type":"tableCell","position":{"start":{"line":95,"column":1},"end":{"line":95,"column":1}},"children":[{"type":"link","url":"https://explore.open223.info/s223/Property.html","position":{"start":{"line":95,"column":1},"end":{"line":95,"column":1}},"children":[{"type":"text","value":"Property","position":{"start":{"line":95,"column":1},"end":{"line":95,"column":1}},"key":"UenjAYwd0N"}],"urlSource":"https://explore.open223.info/s223/Property.html","key":"JcBN0fTwo7"}],"key":"dJEM32IRTA"},{"type":"tableCell","position":{"start":{"line":95,"column":1},"end":{"line":95,"column":1}},"children":[{"type":"link","url":"https://explore.open223.info/s223/EnumeratedObservableProperty.html","position":{"start":{"line":95,"column":1},"end":{"line":95,"column":1}},"children":[{"type":"text","value":"EnumeratedObservableProperty","position":{"start":{"line":95,"column":1},"end":{"line":95,"column":1}},"key":"UOMXj4eVu7"}],"urlSource":"https://explore.open223.info/s223/EnumeratedObservableProperty.html","key":"D5VDxwyl7l"}],"key":"RGUt22Jnyk"},{"type":"tableCell","position":{"start":{"line":95,"column":1},"end":{"line":95,"column":1}},"children":[{"type":"text","value":"226","position":{"start":{"line":95,"column":1},"end":{"line":95,"column":1}},"key":"zM8MGBDTqu"}],"key":"OQzpc2HkWq"}],"key":"po7L6nuj5h"}],"key":"L5iOJ43Msl"},{"type":"heading","depth":2,"position":{"start":{"line":98,"column":1},"end":{"line":98,"column":1}},"children":[{"type":"text","value":"Load and Validate Model","position":{"start":{"line":98,"column":1},"end":{"line":98,"column":1}},"key":"yHwMB4Ljw1"}],"identifier":"load-and-validate-model","label":"Load and Validate Model","html_id":"load-and-validate-model","implicit":true,"key":"U6MrxmLo1l"},{"type":"paragraph","position":{"start":{"line":100,"column":1},"end":{"line":101,"column":1}},"children":[{"type":"text","value":"This code uses the ","position":{"start":{"line":100,"column":1},"end":{"line":100,"column":1}},"key":"aRiFbQVms2"},{"type":"link","url":"https://github.com/NREL/BuildingMOTIF","position":{"start":{"line":100,"column":1},"end":{"line":100,"column":1}},"children":[{"type":"text","value":"BuildingMOTIF","position":{"start":{"line":100,"column":1},"end":{"line":100,"column":1}},"key":"INtTAiXhoY"}],"urlSource":"https://github.com/NREL/BuildingMOTIF","error":true,"key":"G4qND2XpbB"},{"type":"text","value":" library to load the 223P ontology and the model file into a temporary in-memory instance.\nIt then validates the model against the ontology. If the model is invalid, it will print the validation report.","position":{"start":{"line":100,"column":1},"end":{"line":100,"column":1}},"key":"fDBKgZRrKD"}],"key":"mG2l9pb6Yj"},{"type":"paragraph","position":{"start":{"line":103,"column":1},"end":{"line":104,"column":1}},"children":[{"type":"text","value":"To run this code, you need to have Java installed on your system. If you do not have Java installed, you can remove the ","position":{"start":{"line":103,"column":1},"end":{"line":103,"column":1}},"key":"Yt6vZ7v9vn"},{"type":"inlineCode","value":"shacl_engine='topquadrant'","position":{"start":{"line":103,"column":1},"end":{"line":103,"column":1}},"key":"vWyaphi1pC"},{"type":"text","value":" parameter from the ","position":{"start":{"line":103,"column":1},"end":{"line":103,"column":1}},"key":"IOAb5XKd1e"},{"type":"inlineCode","value":"BuildingMOTIF","position":{"start":{"line":103,"column":1},"end":{"line":103,"column":1}},"key":"SUbf9Za4xL"},{"type":"text","value":" constructor.\nBe warned that without the ","position":{"start":{"line":103,"column":1},"end":{"line":103,"column":1}},"key":"umHAPYSvf8"},{"type":"inlineCode","value":"shacl_engine='topquadrant'","position":{"start":{"line":103,"column":1},"end":{"line":103,"column":1}},"key":"TlQvQZZpto"},{"type":"text","value":" parameter, the validation process will be slower.","position":{"start":{"line":103,"column":1},"end":{"line":103,"column":1}},"key":"cesb1rI6hq"}],"key":"zZCs0jr9vE"},{"type":"admonition","kind":"note","children":[{"type":"admonitionTitle","children":[{"type":"text","value":"BuildingMOTIF installation","position":{"start":{"line":106,"column":1},"end":{"line":106,"column":1}},"key":"nK5c15hJsw"}],"key":"ZPMxwgDyEg"},{"type":"paragraph","position":{"start":{"line":108,"column":1},"end":{"line":108,"column":1}},"children":[{"type":"text","value":"To install the ","position":{"start":{"line":108,"column":1},"end":{"line":108,"column":1}},"key":"xkPC4ImMA0"},{"type":"inlineCode","value":"buildingmotif","position":{"start":{"line":108,"column":1},"end":{"line":108,"column":1}},"key":"x2WMDxeOJg"},{"type":"text","value":" library, you can use the following command:","position":{"start":{"line":108,"column":1},"end":{"line":108,"column":1}},"key":"yOJahVqDcq"}],"key":"JQndFJ9Z7X"},{"type":"code","lang":"shell","value":"pip install 'buildingmotif[topquadrant] @ git+https://github.com/NREL/buildingmotif.git@develop'","position":{"start":{"line":110,"column":1},"end":{"line":112,"column":1}},"key":"nQcNuuqRZa"},{"type":"paragraph","position":{"start":{"line":114,"column":1},"end":{"line":114,"column":1}},"children":[{"type":"text","value":"If you do not have Java installed, you can use the following command to install the library:","position":{"start":{"line":114,"column":1},"end":{"line":114,"column":1}},"key":"Lg4wHVKvJM"}],"key":"nsPAgeGZg2"},{"type":"code","lang":"shell","value":"pip install 'buildingmotif @ git+https://github.com/NREL/buildingmotif.git@develop'","position":{"start":{"line":116,"column":1},"end":{"line":118,"column":1}},"key":"AQvXoCyonM"}],"class":"dropdown","key":"k2Z2Fp4hPz"}],"key":"HaSIZ4H5q1"},{"type":"block","kind":"notebook-code","children":[{"type":"code","lang":"python","executable":true,"value":"from buildingmotif import BuildingMOTIF\nfrom buildingmotif.dataclasses import Library, Model\nimport ontoenv\nimport logging\n\n# Create a BuildingMOTIF object. If you do not have Java installed, remove the \"shacl_engine\" parameter\nbm = BuildingMOTIF('sqlite://', shacl_engine='topquadrant', log_level=logging.ERROR)\n\n# load 223P library. We will load a recent copy from the models.open223.info\n# git repository; later, we will load this from the location of the actual standard\ns223 = Library.load(ontology_graph=\"https://open223.info/223p.ttl\", infer_templates=False, run_shacl_inference=False)\nunit = Library.load(ontology_graph=\"http://qudt.org/3.1.1/vocab/unit\", infer_templates=False, run_shacl_inference=False)\nquantitykind = Library.load(ontology_graph=\"http://qudt.org/3.1.1/vocab/quantitykind\", infer_templates=False, run_shacl_inference=False)\n\n# load the model into the BuildingMOTIF instance\nmodel = Model.create(\"urn:pnnl-bdg3-2\")\nmodel.graph.parse(\"https://models.open223.info/pnnl-bdg3-2.ttl\")\n\n# validate the model against 223P ontology\nctx = model.validate([s223.get_shape_collection(),\n                      unit.get_shape_collection(),\n                      quantitykind.get_shape_collection()],\n                     error_on_missing_imports=False)\n\n# print the validation result\nprint(f\"Model is valid: {ctx.valid}\")\n\n# if the model is invalid, print the validation report\nif not ctx.valid:\n    print(ctx.report_string[:1000]) # first 1000 characters of the report\n\n# BuildingMOTIF can also interpret the report to provide recommendations on fixes\nfor focus_node, diffs in ctx.get_reasons_with_severity(\"Violation\").items():\n    if len(diffs) == 0:\n        continue\n    print(focus_node)\n    for diff in diffs:\n        print(\"  - \" + diff.reason())","key":"X5uCHdNy8W"},{"type":"outputs","id":"FtMuBOdFGuiH4UKuQuOxh","children":[{"type":"output","children":[],"jupyter_data":{"output_type":"stream","name":"stdout","text":"Model is valid: 0\nValidation Report\nConforms: False\n\nValidation Results (2612):\n\n--- Result 1 ---\nSeverity: sh:Violation\nFocus Node: <http://speckle.xyz/streams/bf7685a6aa/objects/c2a281dbb365e205175d77ff574b4dac>\nMessage: s223: A `PhysicalSpace` shall be associated with zero or more contained `PhysicalSpace`s using the relation `contains`.\nPath: ns1:contains\nValue: <http://speckle.xyz/streams/bf7685a6aa/objects/bb735c1fd5e7bce4e542eb2535083e45>\nSource Constraint: sh:ClassConstraintComponent\nSource Shape: <urn:well-known/8b876882>\n\n--- Result 2 ---\nSeverity: sh:Violation\nFocus Node: <http://speckle.xyz/streams/bf7685a6aa/objects/c2a281dbb365e205175d77ff574b4dac>\nMessage: s223: A `PhysicalSpace` shall be associated with zero or more contained `PhysicalSpace`s using the relation `contains`.\nPath: ns1:contains\nValue: <http://speckle.xyz/streams/bf7685a6aa/objects/0152b9161ed0a0d6e3ae6919ab77ab11>\nSource Constraint: sh:ClassConstraintComponent\nSource Shape: <urn:well-known/8b876882>\n\n--- Result 3 ---\nSeveri\n"},"key":"qW8vjXGUW0"},{"type":"output","children":[],"jupyter_data":{"output_type":"stream","name":"stdout","text":"http://speckle.xyz/streams/bf7685a6aa/objects/4a9ba07841c2037...","hash":"2d4cbb6dbd823db722301ab0bbb644e4","path":"/build/2d4cbb6dbd823db722301ab0bbb644e4.txt"},"key":"mYmHy9tNDc"}],"key":"qVZ0nqp52E"}],"key":"gqcoWgHyWh"}],"key":"YdOU0odKTR"},"references":{"cite":{"order":[],"data":{}}},"footer":{"navigation":{"prev":{"title":"LBNL Example Building 3 Model 1","url":"/lbnl-bdg3-1","group":"Example Buildings"},"next":{"title":"LBNL Example Building 4 Model 1","url":"/lbnl-bdg4-1","group":"Example Buildings"}}},"domain":"http://localhost:3000"}